README.md
setup.py
django_gdpr_ready.egg-info/PKG-INFO
django_gdpr_ready.egg-info/SOURCES.txt
django_gdpr_ready.egg-info/dependency_links.txt
django_gdpr_ready.egg-info/not-zip-safe
django_gdpr_ready.egg-info/top_level.txt
gdpr/__init__.py