Metadata-Version: 1.0
Name: django-gdpr-ready
Version: 0.1
Summary: Django GDPR Compliance
Home-page: https://github.com/GDPR-ready/django-gdpr-ready
Author: Vikas Mishra
Author-email: vikasmishra95@gmail.com
License: MIT
Platform: UNKNOWN
